<?xml version="1.0" encoding="ISO-8859-1"?>
<response>
<sqCand>280000000012</sqCand>
<sgUe>BR</sgUe>
<name><![CDATA[ ANTÔNIO PEDRO DE SIQUEIRA INDIO DA COSTA ]]></name>
<numero>45</numero>
<partido><![CDATA[ DEM ]]></partido>
<sqCand>280000000004</sqCand>
<sgUe>BR</sgUe>
<name><![CDATA[ CLÁUDIA ALVES DURANS ]]></name>
<numero>16</numero>
<partido><![CDATA[ PSTU ]]></partido>
<sqCand>280000000018</sqCand>
<sgUe>BR</sgUe>
<name><![CDATA[ EDMILSON SILVA COSTA ]]></name>
<numero>21</numero>
<partido><![CDATA[ PCB ]]></partido>
<sqCand>280000000008</sqCand>
<sgUe>BR</sgUe>
<name><![CDATA[ EDSON DORTA SILVA ]]></name>
<numero>29</numero>
<partido><![CDATA[ PCO ]]></partido>
<sqCand>280000000002</sqCand>
<sgUe>BR</sgUe>
<name><![CDATA[ GUILHERME PEIRÃO LEAL ]]></name>
<numero>43</numero>
<partido><![CDATA[ PV ]]></partido>
<sqCand>280000000020</sqCand>
<sgUe>BR</sgUe>
<name><![CDATA[ HAMILTON MOREIRA DE ASSIS ]]></name>
<numero>50</numero>
<partido><![CDATA[ PSOL ]]></partido>
<sqCand>280000000016</sqCand>
<sgUe>BR</sgUe>
<name><![CDATA[ JOSE PAULO DA SILVA NETO ]]></name>
<numero>27</numero>
<partido><![CDATA[ PSDC ]]></partido>
<sqCand>280000000010</sqCand>
<sgUe>BR</sgUe>
<name><![CDATA[ LUIZ EDUARDO AYRES DUARTE ]]></name>
<numero>28</numero>
<partido><![CDATA[ PRTB ]]></partido>
<sqCand>280000000006</sqCand>
<sgUe>BR</sgUe>
<name><![CDATA[ MICHEL MIGUEL ELIAS TEMER LULIA ]]></name>
<numero>13</numero>
<partido><![CDATA[ PMDB ]]></partido>
</response>
