<?xml version="1.0" encoding="ISO-8859-1"?>
<response>
<sqCand>70000000713</sqCand>
<sgUe>DF</sgUe>
<name><![CDATA[ ANNA CHRISTINA KUBITSCHEK BARBARÁ PEREIRA ]]></name>
<numero>255</numero>
<partido><![CDATA[ DEM ]]></partido>
<sqCand>70000000871</sqCand>
<sgUe>DF</sgUe>
<name><![CDATA[ ANTÔNIO JOSÉ ANDRADE ROCHA ]]></name>
<numero>433</numero>
<partido><![CDATA[ PV ]]></partido>
<sqCand>70000000150</sqCand>
<sgUe>DF</sgUe>
<name><![CDATA[ CARLOS SHIGUEO KOBAYASHI ]]></name>
<numero>190</numero>
<partido><![CDATA[ PSL ]]></partido>
<sqCand>70000000055</sqCand>
<sgUe>DF</sgUe>
<name><![CDATA[ CLAYTON DE SOUZA AVELAR ]]></name>
<numero>501</numero>
<partido><![CDATA[ PSOL ]]></partido>
<sqCand>70000001203</sqCand>
<sgUe>DF</sgUe>
<name><![CDATA[ FRANCISCO JOSÉ DE OLIVEIRA FERRAZ ]]></name>
<numero>255</numero>
<partido><![CDATA[ PRTB ]]></partido>
<sqCand>70000000004</sqCand>
<sgUe>DF</sgUe>
<name><![CDATA[ FRANCISCO JOSE TARGINO ]]></name>
<numero>160</numero>
<partido><![CDATA[ PSTU ]]></partido>
<sqCand>70000000649</sqCand>
<sgUe>DF</sgUe>
<name><![CDATA[ HELIO JOSE DA SILVA LIMA ]]></name>
<numero>400</numero>
<partido><![CDATA[ PT ]]></partido>
<sqCand>70000000094</sqCand>
<sgUe>DF</sgUe>
<name><![CDATA[ IVO FERREIRA BRITO ]]></name>
<numero>290</numero>
<partido><![CDATA[ PCO ]]></partido>
<sqCand>70000001113</sqCand>
<sgUe>DF</sgUe>
<name><![CDATA[ JOÃO BATISTA DE CASTRO ]]></name>
<numero>212</numero>
<partido><![CDATA[ PCB ]]></partido>
<sqCand>70000000056</sqCand>
<sgUe>DF</sgUe>
<name><![CDATA[ MARCELLO CAVALCANTI BARRA ]]></name>
<numero>500</numero>
<partido><![CDATA[ PSOL ]]></partido>
<sqCand>70000000151</sqCand>
<sgUe>DF</sgUe>
<name><![CDATA[ NICODEMOS RIBEIRO SAMPAIO ]]></name>
<numero>178</numero>
<partido><![CDATA[ PSL ]]></partido>
<sqCand>70000000716</sqCand>
<sgUe>DF</sgUe>
<name><![CDATA[ OSORIO ADRIANO FILHO ]]></name>
<numero>456</numero>
<partido><![CDATA[ DEM ]]></partido>
<sqCand>70000000874</sqCand>
<sgUe>DF</sgUe>
<name><![CDATA[ WASHINGTON LUIZ DE SOUZA VALLE ]]></name>
<numero>432</numero>
<partido><![CDATA[ PV ]]></partido>
<sqCand>70000000650</sqCand>
<sgUe>DF</sgUe>
<name><![CDATA[ WILMAR LACERDA ]]></name>
<numero>123</numero>
<partido><![CDATA[ PDT ]]></partido>
</response>
