<?xml version="1.0" encoding="ISO-8859-1"?>
<response>
<sqCand>70000000092</sqCand>
<sgUe>DF</sgUe>
<name><![CDATA[ EXPEDITO CARNEIRO DE MENDONÇA ]]></name>
<numero>29</numero>
<partido><![CDATA[ PCO ]]></partido>
<sqCand>70000001131</sqCand>
<sgUe>DF</sgUe>
<name><![CDATA[ JOÃO BATISTA DE JESUS SILVA ]]></name>
<numero>21</numero>
<partido><![CDATA[ PCB ]]></partido>
<sqCand>70000000676</sqCand>
<sgUe>DF</sgUe>
<name><![CDATA[ JOFRAN FREJAT ]]></name>
<numero>20</numero>
<partido><![CDATA[ PR ]]></partido>
<sqCand>70000000869</sqCand>
<sgUe>DF</sgUe>
<name><![CDATA[ LUIZ CARLOS DE ALBURQUERQUE MARANHÃO ]]></name>
<numero>43</numero>
<partido><![CDATA[ PV ]]></partido>
<sqCand>70000000646</sqCand>
<sgUe>DF</sgUe>
<name><![CDATA[ NELSON TADEU FILIPPELLI ]]></name>
<numero>13</numero>
<partido><![CDATA[ PMDB ]]></partido>
<sqCand>70000000147</sqCand>
<sgUe>DF</sgUe>
<name><![CDATA[ PAULO FERNANDO SANTOS DE VASCONCELOS ]]></name>
<numero>17</numero>
<partido><![CDATA[ PTN ]]></partido>
<sqCand>70000000002</sqCand>
<sgUe>DF</sgUe>
<name><![CDATA[ ROSA OLIMPIA MARTINS DE MELO ]]></name>
<numero>16</numero>
<partido><![CDATA[ PSTU ]]></partido>
<sqCand>70000000052</sqCand>
<sgUe>DF</sgUe>
<name><![CDATA[ TERESINHA MONTEIRO OLIVEIRA ]]></name>
<numero>50</numero>
<partido><![CDATA[ PSOL ]]></partido>
</response>
